LICENSE.txt
README.md
setup.py
ScholarCodeCollective/__init__.py
ScholarCodeCollective/cli.py
ScholarCodeCollective.egg-info/PKG-INFO
ScholarCodeCollective.egg-info/SOURCES.txt
ScholarCodeCollective.egg-info/dependency_links.txt
ScholarCodeCollective.egg-info/entry_points.txt
ScholarCodeCollective.egg-info/top_level.txt
ScholarCodeCollective/community_regionalization/__init__.py
ScholarCodeCollective/community_regionalization/greedy_algorithm.py
ScholarCodeCollective/distributional_regionalization/__init__.py
ScholarCodeCollective/distributional_regionalization/functions.py
ScholarCodeCollective/hub_identification/__init__.py
ScholarCodeCollective/hub_identification/functions.py
ScholarCodeCollective/hypergraph_binning/__init__.py
ScholarCodeCollective/hypergraph_binning/functions.py
ScholarCodeCollective/population_clustering/__init__.py
ScholarCodeCollective/population_clustering/functions.py
tests/__init__.py