Metadata-Version: 2.1
Name: ScholarCodeCollective
Version: 0.1.8.7
Summary: A collective library for the code behind several academic papers
Home-page: https://scholarcodecollective.readthedocs.io/en/latest/index.html
Author: Author Name
Author-email: baiyueh@hku.hk
License: The Unlicense
Requires-Python: >=3.9, <3.12
License-File: LICENSE.txt
